Metadata-Version: 2.1
Name: wrapper-Requerst
Version: 0.0.1
Summary: Wrapper não oficial do Requerst
Author: Serial Tecnologias
Author-email: serial@outlook.com.br
License: MIT License
Keywords: Requerst
License-File: LICENCE
Requires-Dist: requests
